[
  {
    "name": "Andaman & Nicobar",
    "capital": "Port Blair"
  },
  {
    "name": "Andhra Pradesh",
    "capital": "Amaravati"
  },
  {
    "name": "Arunachal Pradesh",
    "capital": "Itanagar"
  },
  {
    "name": "Assam",
    "capital": "Dispur"
  },
  {
    "name": "Bihar",
    "capital": "Patna"
  },
  {
    "name": "Chandigarh",
    "capital": "Chandigarh"
  },
  {
    "name": "Chhattisgarh",
    "capital": "Raipur"
  },
  {
    "name": "Dadra and Nagar Haveli and Daman and Diu",
    "capital": "Daman, Daman and Diu"
  },
  {
    "name": "Delhi",
    "capital": "New Delhi"
  },
  {
    "name": "Goa",
    "capital": "Panaji"
  },
  {
    "name": "Gujarat",
    "capital": "Gandhinagar"
  },
  {
    "name": "Haryana",
    "capital": "Chandigarh"
  },
  {
    "name": "Himachal Pradesh",
    "capital": "Shimla"
  },
  {
    "name": "Jammu & Kashmir",
    "capital": "Srinagar"
  },
  {
    "name": "Jharkhand",
    "capital": "Ranchi"
  },
  {
    "name": "Karnataka",
    "capital": "Bengaluru"
  },
  {
    "name": "Kerala",
    "capital": "Thiruvananthapuram"
  },
  {
    "name": "Lakshadweep",
    "capital": "Kavaratti"
  },
  {
    "name": "Ladakh",
    "capital": "Leh"
  },
  {
    "name": "Madhya Pradesh",
    "capital": "Bhopal"
  },
  {
    "name": "Maharashtra",
    "capital": "Mumbai"
  },
  {
    "name": "Manipur",
    "capital": "Imphal"
  },
  {
    "name": "Meghalaya",
    "capital": "Shillong"
  },
  {
    "name": "Mizoram",
    "capital": "Aizawl"
  },
  {
    "name": "Nagaland",
    "capital": "Kohima"
  },
  {
    "name": "Odisha",
    "capital": "Bhubaneswar"
  },
  {
    "name": "Puducherry",
    "capital": "Puducherry"
  },
  {
    "name": "Punjab",
    "capital": "Chandigarh"
  },
  {
    "name": "Rajasthan",
    "capital": "Jaipur"
  },
  {
    "name": "Sikkim",
    "capital": "Gangtok"
  },
  {
    "name": "Tamil Nadu",
    "capital": "Chennai"
  },
  {
    "name": "Telangana",
    "capital": "Hyderabad"
  },
  {
    "name": "Tripura",
    "capital": "Agartala"
  },
  {
    "name": "Uttar Pradesh",
    "capital": "Lucknow"
  },
  {
    "name": "Uttarakhand",
    "capital": "Dehradun"
  },
  {
    "name": "West Bengal",
    "capital": "Kolkata"
  }
]